pelicantool/__init__.py
pelicantool/__main__.py
pelicantool/article.py
pelicantool/exceptions.py
pelicantool/parser.py
pelicantool/utils.py
pelicantool/config/pelicantool.toml
pelicantool-0.7.0.dist-info/DESCRIPTION.rst
pelicantool-0.7.0.dist-info/METADATA
pelicantool-0.7.0.dist-info/RECORD
pelicantool-0.7.0.dist-info/WHEEL
pelicantool-0.7.0.dist-info/entry_points.txt
pelicantool-0.7.0.dist-info/metadata.json
pelicantool-0.7.0.dist-info/top_level.txt
