Metadata-Version: 2.0
Name: pelicantool
Version: 0.7.0
Summary: pelican auto tool
Home-page: https://github.com/xiaojieluo/pelicantool
Author: Luo Xiaojie
Author-email: xiaojieluoff@gmail.com
License: GNU GENERAL PUBLIC LICENSE
Requires-Dist: requests (>=2.18.4)
Requires-Dist: six (>=1.10.0)
Requires-Dist: toml (>=0.9.4)
